{
  "hash": "8cfd5664",
  "browserHash": "254b1c56",
  "optimized": {
    "vue": {
      "src": "../../../../node_modules/.pnpm/vue@3.3.4/node_modules/vue/dist/vue.runtime.esm-bundler.js",
      "file": "vue.js",
      "fileHash": "47509a66",
      "needsInterop": false
    },
    "vitepress > @vue/devtools-api": {
      "src": "../../../../node_modules/.pnpm/@vue+devtools-api@6.5.0/node_modules/@vue/devtools-api/lib/esm/index.js",
      "file": "vitepress___@vue_devtools-api.js",
      "fileHash": "02455d4f",
      "needsInterop": false
    },
    "vitepress > @vueuse/integrations/useFocusTrap": {
      "src": "../../../../node_modules/.pnpm/@vueuse+integrations@10.4.1_focus-trap@7.5.2_vue@3.3.4/node_modules/@vueuse/integrations/useFocusTrap.mjs",
      "file": "vitepress___@vueuse_integrations_useFocusTrap.js",
      "fileHash": "32d0b907",
      "needsInterop": false
    },
    "vitepress > mark.js/src/vanilla.js": {
      "src": "../../../../node_modules/.pnpm/mark.js@8.11.1/node_modules/mark.js/src/vanilla.js",
      "file": "vitepress___mark__js_src_vanilla__js.js",
      "fileHash": "0cea827c",
      "needsInterop": false
    },
    "vitepress > minisearch": {
      "src": "../../../../node_modules/.pnpm/minisearch@6.1.0/node_modules/minisearch/dist/es/index.js",
      "file": "vitepress___minisearch.js",
      "fileHash": "191b4fde",
      "needsInterop": false
    },
    "@vitepress-demo-preview/component": {
      "src": "../../../../node_modules/.pnpm/@vitepress-demo-preview+component@2.3.2_vitepress@1.0.0-rc.7_vue@3.3.4/node_modules/@vitepress-demo-preview/component/dist/preview-component.js",
      "file": "@vitepress-demo-preview_component.js",
      "fileHash": "d61a684d",
      "needsInterop": false
    }
  },
  "chunks": {
    "chunk-67UUJLDS": {
      "file": "chunk-67UUJLDS.js"
    }
  }
}